ecb_rates/__init__.py
ecb_rates/ecb_rates.py
ecb_currency_exchange_rate-0.1.4.dist-info/METADATA
ecb_currency_exchange_rate-0.1.4.dist-info/WHEEL
ecb_currency_exchange_rate-0.1.4.dist-info/top_level.txt
ecb_currency_exchange_rate-0.1.4.dist-info/RECORD
