Metadata-Version: 2.4
Name: ecb-currency-exchange-rate
Version: 0.1.4
Summary: Fetch and process historical daily currency exchange rate from the ECB
Author-email: Odessa Ren <odessa.ren@hotmail.com>
License-Expression: MIT
Project-URL: Homepage, https://github.com/OdessaR/ecb-currency-exchange-rate
Project-URL: Repository, https://github.com/OdessaR/ecb-currency-exchange-rate
Requires-Python: >=3.6
Requires-Dist: requests
